treefarms/example.py
treefarms/libgosdt.pyd
treefarms/__init__.py
treefarms/model/encoder.py
treefarms/model/model_set.py
treefarms/model/threshold_guess.py
treefarms/model/treefarms.py
treefarms/model/tree_classifier.py
treefarms/model/__init__.py
treefarms/model/imbalance/osdt_imb_v9.py
treefarms/model/imbalance/osdt_sup.py
treefarms/model/imbalance/rule.py
treefarms/model/imbalance/__init__.py
treefarms-0.2.4.dist-info/DELVEWHEEL
treefarms-0.2.4.dist-info/LICENSE
treefarms-0.2.4.dist-info/METADATA
treefarms-0.2.4.dist-info/RECORD
treefarms-0.2.4.dist-info/top_level.txt
treefarms-0.2.4.dist-info/WHEEL
treefarms.libs/.load-order-treefarms-0.2.4
treefarms.libs/gmp-10.dll
treefarms.libs/msvcp140.dll
treefarms.libs/tbb12.dll
treefarms.libs/tbbmalloc.dll
treefarms.libs/vcruntime140_1.dll
