Metadata-Version: 2.1
Name: treefarms
Version: 0.2.4
Summary: Implementation of Trees FAst RashoMon Sets
Home-page: https://github.com/ubc-systopia/treeFarms
Author: UBC Systopia Research Lab
License: BSD 3-Clause
Platform: UNKNOWN
Requires-Python: >=3.7
Requires-Dist: setuptools
Requires-Dist: wheel
Requires-Dist: attrs
Requires-Dist: packaging >=20.9
Requires-Dist: pandas
Requires-Dist: scikit-learn
Requires-Dist: sortedcontainers
Requires-Dist: gmpy2
Requires-Dist: matplotlib
Requires-Dist: tqdm
Requires-Dist: timbertrek
Requires-Dist: editables ==0.2 ; python_version > "3.0"
